Chapter1/suggested_experiments/gate_level_grater_than/gate_level_grater_than.vhd
library ieee;
use ieee.std_logic_1164.all;
use ieee.numeric_std.all;


entity gt2 is port(
                    a,b : in std_logic_vector(1 downto 0);
                    agtb : out std_logic
                  );
end gt2;

architecture logic of gt2 is 
begin 
  agtb <= '1' when unsigned(a) > unsigned(b) else '0';
end logic;

Chapter1/suggested_experiments/gate_level_grater_than/tb_gate_level_grater_than.vhd
library ieee;
use ieee.std_logic_1164.all;
use ieee.numeric_std.all;


entity tb_gate_level_grater_than is 
  end tb_gate_level_grater_than;

architecture behavior of tb_gate_level_grater_than is 
  signal a,b : std_logic_vector (1 downto 0);
  signal agtb : std_logic;

  component gt2
    port(
          a,b : in std_logic_vector (1 downto 0);
          agtb : out std_logic
        );
  end component;

begin 
  uut: gt2 port map(a => a ,b => b,agtb => agtb);
  stim_proc: process                       
  begin    
    a <= "00"; b <= "00"; wait for 10 ns;
    a <= "00"; b <= "01"; wait for 10 ns;
    a <= "00"; b <= "10"; wait for 10 ns;
    a <= "00"; b <= "11"; wait for 10 ns;
    a <= "01"; b <= "00"; wait for 10 ns;
    a <= "01"; b <= "01"; wait for 10 ns;
    a <= "01"; b <= "10"; wait for 10 ns;
    a <= "01"; b <= "11"; wait for 10 ns;
    a <= "10"; b <= "00"; wait for 10 ns;
    a <= "10"; b <= "01"; wait for 10 ns;
    a <= "10"; b <= "10"; wait for 10 ns;                           
    a <= "10"; b <= "11"; wait for 10 ns;
    a <= "11"; b <= "00"; wait for 10 ns;
    a <= "11"; b <= "01"; wait for 10 ns;
    a <= "11"; b <= "10"; wait for 10 ns;
    a <= "11"; b <= "11"; wait for 10 ns;      
    wait;
  end process;
end behavior;

Chapter1/suggested_experiments/gate_level_grater_than/wave_gt.vcd
$date
  Thu Jul 17 07:26:15 2025
$end
$version
  GHDL v0
$end
$timescale
  1 fs
$end
$scope module standard $end
$upscope $end
$scope module std_logic_1164 $end
$upscope $end
$scope module numeric_std $end
$upscope $end
$scope module tb_gate_level_grater_than $end
$var reg 2 ! a[1:0] $end
$var reg 2 " b[1:0] $end
$var reg 1 # agtb $end
$scope module uut $end
$var reg 2 $ a[1:0] $end
$var reg 2 % b[1:0] $end
$var reg 1 & agtb $end
$upscope $end
$upscope $end
$enddefinitions $end
#0
b00 !
b00 "
0#
b00 $
b00 %
0&
#10000000
b01 "
b01 %
#20000000
b10 "
b10 %
#30000000
b11 "
b11 %
#40000000
b01 !
b00 "
1#
b01 $
b00 %
1&
#50000000
b01 "
0#
b01 %
0&
#60000000
b10 "
b10 %
#70000000
b11 "
b11 %
#80000000
b10 !
b00 "
1#
b10 $
b00 %
1&
#90000000
b01 "
b01 %
#100000000
b10 "
0#
b10 %
0&
#110000000
b11 "
b11 %
#120000000
b11 !
b00 "
1#
b11 $
b00 %
1&
#130000000
b01 "
b01 %
#140000000
b10 "
b10 %
#150000000
b11 "
0#
b11 %
0&
