Chapter1/example_2/eq1.vhd
library ieee;
use ieee.std_logic_1164.all;
use ieee.numeric_std.all;

entity eq1 is port(
                    i0,i1 : in std_logic;
                    eq    : out std_logic
                         );
end eq1;

architecture sop_arch of eq1 is 
        signal p0,p1 : std_logic;
      begin
        --sum of two products terms
        eq <= p0 or p1;
        -- products terms:
        p0 <= (not i0) and (not i1);
        p1 <= i0 and i1 ;
end sop_arch;

Chapter1/example_2/eq2.vhd
library ieee;
use ieee.std_logic_1164.all;

entity eq2 is
  port (
    a, b  : in  std_logic_vector(1 downto 0);
    aeqb  : out std_logic
  );
end eq2;

architecture struc_arch of eq2 is
  signal e0, e1 : std_logic;
begin
  -- Инстанцирование 1-битных компараторов
  eq_bit0_unit : entity work.eq1(sop_arch)
    port map (
      i0 => a(0),
      i1 => b(0),
      eq => e0
    );

  eq_bit1_unit : entity work.eq1(sop_arch)
    port map (
      i0 => a(1),
      i1 => b(1),
      eq => e1
    );

  -- Объединение результатов
  aeqb <= e0 and e1;
end struc_arch;

Chapter1/example_2/tb_eq2.vhd
library ieee;
use ieee.std_logic_1164.all;

entity tb_eq2 is
end tb_eq2;

architecture behavior of tb_eq2 is
  signal a, b  : std_logic_vector(1 downto 0);
  signal aeqb  : std_logic;

  component eq2
    port (
      a, b  : in  std_logic_vector(1 downto 0);
      aeqb  : out std_logic
    );
  end component;

begin
  uut: eq2 port map(a => a, b => b, aeqb => aeqb);

  stim_proc: process
  begin
    a <= "00"; b <= "00"; wait for 10 ns;
    a <= "00"; b <= "01"; wait for 10 ns;
    a <= "00"; b <= "10"; wait for 10 ns;
    a <= "00"; b <= "11"; wait for 10 ns;
    a <= "01"; b <= "00"; wait for 10 ns;
    a <= "01"; b <= "01"; wait for 10 ns;
    a <= "01"; b <= "10"; wait for 10 ns;
    a <= "01"; b <= "11"; wait for 10 ns;
    a <= "10"; b <= "00"; wait for 10 ns;
    a <= "10"; b <= "01"; wait for 10 ns;
    a <= "10"; b <= "10"; wait for 10 ns;
    a <= "10"; b <= "11"; wait for 10 ns;
    a <= "11"; b <= "00"; wait for 10 ns;
    a <= "11"; b <= "01"; wait for 10 ns;
    a <= "11"; b <= "10"; wait for 10 ns;
    a <= "11"; b <= "11"; wait for 10 ns;      
    wait;
  end process;
end behavior;

Chapter1/example_2/wave.vcd
$date
  Wed Jul 16 11:57:40 2025
$end
$version
  GHDL v0
$end
$timescale
  1 fs
$end
$scope module standard $end
$upscope $end
$scope module std_logic_1164 $end
$upscope $end
$scope module numeric_std $end
$upscope $end
$scope module tb_eq2 $end
$var reg 2 ! a[1:0] $end
$var reg 2 " b[1:0] $end
$var reg 1 # aeqb $end
$scope module uut $end
$var reg 2 $ a[1:0] $end
$var reg 2 % b[1:0] $end
$var reg 1 & aeqb $end
$var reg 1 ' e0 $end
$var reg 1 ( e1 $end
$scope module eq_bit0_unit $end
$var reg 1 ) i0 $end
$var reg 1 * i1 $end
$var reg 1 + eq $end
$var reg 1 , p0 $end
$var reg 1 - p1 $end
$upscope $end
$scope module eq_bit1_unit $end
$var reg 1 . i0 $end
$var reg 1 / i1 $end
$var reg 1 0 eq $end
$var reg 1 1 p0 $end
$var reg 1 2 p1 $end
$upscope $end
$upscope $end
$upscope $end
$enddefinitions $end
#0
b00 !
b00 "
1#
b00 $
b00 %
1&
1'
1(
0)
0*
1+
1,
0-
0.
0/
10
11
02
#10000000
b01 "
0#
b01 %
0&
0'
1*
0+
0,
#20000000
b10 "
b10 %
1'
0(
0*
1+
1,
1/
00
01
#30000000
b11 "
b11 %
0'
1*
0+
0,
#40000000
b01 !
b00 "
b01 $
b00 %
1(
1)
0*
0/
10
11
#50000000
b01 "
1#
b01 %
1&
1'
1*
1+
1-
#60000000
b10 "
0#
b10 %
0&
0'
0(
0*
0+
0-
1/
00
01
#70000000
b11 "
b11 %
1'
1*
1+
1-
#80000000
b10 !
b00 "
b10 $
b00 %
0)
0*
1,
0-
1.
0/
#90000000
b01 "
b01 %
0'
1*
0+
0,
#100000000
b10 "
1#
b10 %
1&
1'
1(
0*
1+
1,
1/
10
12
#110000000
b11 "
0#
b11 %
0&
0'
1*
0+
0,
#120000000
b11 !
b00 "
b11 $
b00 %
0(
1)
0*
0/
00
02
#130000000
b01 "
b01 %
1'
1*
1+
1-
#140000000
b10 "
b10 %
0'
1(
0*
0+
0-
1/
10
12
#150000000
b11 "
1#
b11 %
1&
1'
1*
1+
1-
